{"nodes":[{"id":"flutter-engine","group":2},{"id":"5u3it","group":0},{"id":"flutter","group":1},{"id":"B3rn475","group":0},{"id":"flutter","group":1},{"id":"Coder-256","group":0},{"id":"DanAlbert","group":0},{"id":"ErikCorryGoogle","group":0},{"id":"flutter","group":1},{"id":"GaryQian","group":0},{"id":"buildroot","group":1},{"id":"flutter","group":1},{"id":"HalCanary","group":0},{"id":"HansMuller","group":0},{"id":"flutter","group":1},{"id":"plugins","group":1},{"id":"HelloCore","group":0},{"id":"Hixie","group":0},{"id":"buildroot","group":1},{"id":"flutter","group":1},{"id":"LeonScroggins","group":0},{"id":"Maxim-Mazurok","group":0},{"id":"MitchRudominer","group":0},{"id":"flutter","group":1},{"id":"NikoYuwono","group":0},{"id":"flutter","group":1},{"id":"Phrohdoh","group":0},{"id":"Piinks","group":0},{"id":"flutter","group":1},{"id":"Qxyat","group":0},{"id":"Rusino","group":0},{"id":"SupSaiYaJin","group":0},{"id":"a-siva","group":0},{"id":"buildroot","group":1},{"id":"flutter","group":1},{"id":"plugins","group":1},{"id":"aam","group":0},{"id":"buildroot","group":1},{"id":"flutter","group":1},{"id":"plugins","group":1},{"id":"aartbik","group":0},{"id":"flutter","group":1},{"id":"abarth","group":0},{"id":"buildroot","group":1},{"id":"flutter","group":1},{"id":"abhishekamit","group":0},{"id":"buildroot","group":1},{"id":"aboodman","group":0},{"id":"adambuchbinder","group":0},{"id":"adazh","group":0},{"id":"flutter","group":1},{"id":"afandria","group":0},{"id":"flutter","group":1},{"id":"agampe","group":0},{"id":"agd","group":0},{"id":"aghassemi","group":0},{"id":"flutter","group":1},{"id":"alanrussian","group":0},{"id":"flutter","group":1},{"id":"plugins","group":1},{"id":"alexmarkov","group":0},{"id":"flutter","group":1},{"id":"alhaad","group":0},{"id":"flutter","group":1},{"id":"alibitek","group":0},{"id":"flutter","group":1},{"id":"plugins","group":1},{"id":"amirh","group":0},{"id":"buildroot","group":1},{"id":"flutter","group":1},{"id":"plugins","group":1},{"id":"ankitdave06","group":0},{"id":"ankurmittal","group":0},{"id":"appsforartists","group":0},{"id":"flutter","group":1},{"id":"apwilson","group":0},{"id":"flutter","group":1},{"id":"arbreng","group":0},{"id":"flutter","group":1},{"id":"asankah","group":0},{"id":"ashawn","group":0},{"id":"behdad","group":0},{"id":"bkonyi","group":0},{"id":"buildroot","group":1},{"id":"flutter","group":1},{"id":"plugins","group":1},{"id":"blasten","group":0},{"id":"flutter","group":1},{"id":"bparrishMines","group":0},{"id":"plugins","group":1},{"id":"brianosman","group":0},{"id":"bsalomon","group":0},{"id":"bungeman","group":0},{"id":"cary-clark","group":0},{"id":"cbracken","group":0},{"id":"buildroot","group":1},{"id":"flutter","group":1},{"id":"cfontas","group":0},{"id":"chadj-at-google","group":0},{"id":"chih-hung","group":0},{"id":"chinmaygarde","group":0},{"id":"buildroot","group":1},{"id":"flutter","group":1},{"id":"plugins","group":1},{"id":"christopherfujino","group":0},{"id":"buildroot","group":1},{"id":"flutter","group":1},{"id":"chunhtai","group":0},{"id":"flutter","group":1},{"id":"clarkezone","group":0},{"id":"flutter-desktop-embedding","group":1},{"id":"cloudwebrtc","group":0},{"id":"11LiveChat","group":1},{"id":"LAUNCHXL-F28027-PWM-Generator","group":1},{"id":"RNTouchVGDemo","group":1},{"id":"args_helper","group":1},{"id":"cloudwebrtc.com","group":1},{"id":"dart-events","group":1},{"id":"dart-protoo-client","group":1},{"id":"dart-sdp-transform","group":1},{"id":"dart-sip-ua","group":1},{"id":"flutter-desktop-embedding","group":1},{"id":"flutter-mediasoup-client","group":1},{"id":"flutter-webrtc","group":1},{"id":"flutter-webrtc-demo","group":1},{"id":"flutter-webrtc-server","group":1},{"id":"flutter_touchvg","group":1},{"id":"go-protoo","group":1},{"id":"ion","group":1},{"id":"libwebrtc-build","group":1},{"id":"peg","group":1},{"id":"pion-webrtc","group":1},{"id":"react-native-touchvg","group":1},{"id":"colinblundell","group":0},{"id":"flutter","group":1},{"id":"colincross","group":0},{"id":"collinjackson","group":0},{"id":"flutter","group":1},{"id":"plugins","group":1},{"id":"cpizano","group":0},{"id":"cpu-chromium","group":0},{"id":"flutter","group":1},{"id":"crelier","group":0},{"id":"flutter","group":1},{"id":"cyanglaz","group":0},{"id":"flutter","group":1},{"id":"plugins","group":1},{"id":"danafergan","group":0},{"id":"danw","group":0},{"id":"dballesteros7","group":0},{"id":"devoncarew","group":0},{"id":"firebase-dart","group":1},{"id":"flutter","group":1},{"id":"flutter-desktop-embedding","group":1},{"id":"plugins","group":1},{"id":"dguralnick","group":0},{"id":"plugins","group":1},{"id":"ditman","group":0},{"id":"dkwingsmt","group":0},{"id":"flutter","group":1},{"id":"dmmoore","group":0},{"id":"dnfield","group":0},{"id":"awesome-flutter","group":1},{"id":"buildroot","group":1},{"id":"flutter","group":1},{"id":"plugins","group":1},{"id":"domenic","group":0},{"id":"domesticmouse","group":0},{"id":"plugins","group":1},{"id":"dpa-g","group":0},{"id":"dragostis","group":0},{"id":"flutter","group":1},{"id":"ds84182","group":0},{"id":"flutter","group":1},{"id":"egdaniel","group":0},{"id":"eglaysher","group":0},{"id":"emembrives","group":0},{"id":"endpress","group":0},{"id":"enh-google","group":0},{"id":"eseidel","group":0},{"id":"flutter","group":1},{"id":"eseidelGoogle","group":0},{"id":"flutter","group":1},{"id":"esprehn","group":0},{"id":"flutter","group":1},{"id":"ethanblake4","group":0},{"id":"ferhatb","group":0},{"id":"flar","group":0},{"id":"flutter","group":1},{"id":"floitschG","group":0},{"id":"flutter","group":1},{"id":"plugins","group":1},{"id":"fmalita","group":0},{"id":"franciscojma86","group":0},{"id":"flutter","group":1},{"id":"flutter-desktop-embedding","group":1},{"id":"freiling","group":0},{"id":"gaaclarke","group":0},{"id":"flutter","group":1},{"id":"gamebox","group":0},{"id":"awesome-flutter","group":1},{"id":"flutter","group":1},{"id":"goderbauer","group":0},{"id":"buildroot","group":1},{"id":"flutter","group":1},{"id":"plugins","group":1},{"id":"gspencergoog","group":0},{"id":"buildroot","group":1},{"id":"flutter","group":1},{"id":"plugins","group":1},{"id":"gw280","group":0},{"id":"hterkelsen","group":0},{"id":"flutter","group":1},{"id":"hugovdm","group":0},{"id":"ianloic","group":0},{"id":"flutter","group":1},{"id":"iansf","group":0},{"id":"flutter","group":1},{"id":"inthroxify","group":0},{"id":"iskakaushik","group":0},{"id":"flutter","group":1},{"id":"plugins","group":1},{"id":"ivk1800","group":0},{"id":"flutter","group":1},{"id":"plugins","group":1},{"id":"j9brown","group":0},{"id":"buildroot","group":1},{"id":"flutter","group":1},{"id":"jabdelmalek","group":0},{"id":"jacob314","group":0},{"id":"flutter","group":1},{"id":"jakobr-google","group":0},{"id":"flutter","group":1},{"id":"plugins","group":1},{"id":"jamesblasco","group":0},{"id":"jamesderlin","group":0},{"id":"flutter","group":1},{"id":"jamesr","group":0},{"id":"buildroot","group":1},{"id":"flutter","group":1},{"id":"jason-simmons","group":0},{"id":"buildroot","group":1},{"id":"flutter","group":1},{"id":"plugins","group":1},{"id":"jbauman42","group":0},{"id":"jensjoha","group":0},{"id":"flutter","group":1},{"id":"jerryzhoujw","group":0},{"id":"jimbeveridge","group":0},{"id":"flutter","group":1},{"id":"jimmycasey","group":0},{"id":"flutter","group":1},{"id":"jimsimon","group":0},{"id":"flutter","group":1},{"id":"jmagman","group":0},{"id":"flutter","group":1},{"id":"johnmccutchan","group":0},{"id":"flutter","group":1},{"id":"johnsonmh","group":0},{"id":"flutter","group":1},{"id":"jonahwilliams","group":0},{"id":"flutter","group":1},{"id":"flutter-desktop-embedding","group":1},{"id":"plugins","group":1},{"id":"josephlr","group":0},{"id":"joshuaseaton","group":0},{"id":"flutter","group":1},{"id":"jreck","group":0},{"id":"jslavitz","group":0},{"id":"flutter","group":1},{"id":"justinmc","group":0},{"id":"flutter","group":1},{"id":"jvanverth","group":0},{"id":"kangwang1988","group":0},{"id":"buildroot","group":1},{"id":"flutter","group":1},{"id":"plugins","group":1},{"id":"keertip","group":0},{"id":"flutter","group":1},{"id":"kevinlindkvist","group":0},{"id":"kf6gpe","group":0},{"id":"buildroot","group":1},{"id":"flutter","group":1},{"id":"konkers","group":0},{"id":"kpozin","group":0},{"id":"flutter","group":1},{"id":"krisgiesing","group":0},{"id":"flutter","group":1},{"id":"flutter-desktop-embedding","group":1},{"id":"kruton","group":0},{"id":"ksimbili","group":0},{"id":"ksk9687","group":0},{"id":"kulakowski","group":0},{"id":"kzietek","group":0},{"id":"lambdabaa","group":0},{"id":"lext-7","group":0},{"id":"flutter","group":1},{"id":"liamappelbe","group":0},{"id":"flutter","group":1},{"id":"liyuqian","group":0},{"id":"buildroot","group":1},{"id":"flutter","group":1},{"id":"long1eu","group":0},{"id":"plugins","group":1},{"id":"loongliu","group":0},{"id":"luigi-rosso","group":0},{"id":"majido","group":0},{"id":"maqnouch","group":0},{"id":"matanlurey","group":0},{"id":"awesome-flutter","group":1},{"id":"flutter","group":1},{"id":"plugins","group":1},{"id":"matthew-carroll","group":0},{"id":"flutter","group":1},{"id":"plugins","group":1},{"id":"matthewtsmith","group":0},{"id":"flutter_barcode_reader","group":1},{"id":"flutterlocation","group":1},{"id":"plugins","group":1},{"id":"mattsarett","group":0},{"id":"flutter","group":1},{"id":"mdakin","group":0},{"id":"flutter","group":1},{"id":"mdebbar","group":0},{"id":"flutter","group":1},{"id":"mdempsky","group":0},{"id":"buildroot","group":1},{"id":"mehmetf","group":0},{"id":"flutter","group":1},{"id":"flutterlocation","group":1},{"id":"plugins","group":1},{"id":"mikejurka","group":0},{"id":"flutter","group":1},{"id":"mimers","group":0},{"id":"mishadynin","group":0},{"id":"flutter","group":1},{"id":"mit-mit","group":0},{"id":"firebase-dart","group":1},{"id":"flutter","group":1},{"id":"plugins","group":1},{"id":"mklim","group":0},{"id":"flutter","group":1},{"id":"plugins","group":1},{"id":"mkustermann","group":0},{"id":"flutter","group":1},{"id":"mmclenna","group":0},{"id":"flutter","group":1},{"id":"mpcomplete","group":0},{"id":"flutter","group":1},{"id":"mraleph","group":0},{"id":"buildroot","group":1},{"id":"flutter","group":1},{"id":"plugins","group":1},{"id":"mravn-google","group":0},{"id":"flutter","group":1},{"id":"plugins","group":1},{"id":"mxia","group":0},{"id":"najeira","group":0},{"id":"flutter","group":1},{"id":"plugins","group":1},{"id":"narayank","group":0},{"id":"nathanrogersgoogle","group":0},{"id":"ncbray","group":0},{"id":"nichtverstehen","group":0},{"id":"plugins","group":1},{"id":"nightwolf-chen","group":0},{"id":"nitramsivart","group":0},{"id":"nona-google","group":0},{"id":"nshahan","group":0},{"id":"nturgut","group":0},{"id":"ojanvafai","group":0},{"id":"flutter","group":1},{"id":"ojhunt","group":0},{"id":"pchampio","group":0},{"id":"flutter-desktop-embedding","group":1},{"id":"go-flutter","group":1},{"id":"petrhosek","group":0},{"id":"flutter","group":1},{"id":"poitch","group":0},{"id":"pombredanne","group":0},{"id":"ppiet","group":0},{"id":"pq","group":0},{"id":"flutter","group":1},{"id":"pulyaevskiy","group":0},{"id":"flutter","group":1},{"id":"plugins","group":1},{"id":"pylaligand","group":0},{"id":"buildroot","group":1},{"id":"flutter","group":1},{"id":"qsr","group":0},{"id":"flutter","group":1},{"id":"rafaelring","group":0},{"id":"rafaelw","group":0},{"id":"flutter","group":1},{"id":"rafern","group":0},{"id":"raggi","group":0},{"id":"raphlinus","group":0},{"id":"reed-at-google","group":0},{"id":"ritesh-malav","group":0},{"id":"rmacnak-google","group":0},{"id":"buildroot","group":1},{"id":"flutter","group":1},{"id":"rmistry","group":0},{"id":"roozbehp","group":0},{"id":"roubert","group":0},{"id":"sbaranov","group":0},{"id":"flutter","group":1},{"id":"schwa423","group":0},{"id":"sethladd","group":0},{"id":"awesome-flutter","group":1},{"id":"firebase-dart","group":1},{"id":"flutter","group":1},{"id":"flutterlocation","group":1},{"id":"plugins","group":1},{"id":"sgraham","group":0},{"id":"flutter","group":1},{"id":"webrtc_mirror","group":1},{"id":"shihaohong","group":0},{"id":"flutter","group":1},{"id":"shoryukenn","group":0},{"id":"sigurdm","group":0},{"id":"flutter","group":1},{"id":"plugins","group":1},{"id":"sivachandra","group":0},{"id":"flutter","group":1},{"id":"siyamed","group":0},{"id":"sjindel-google","group":0},{"id":"flutter","group":1},{"id":"skia-flutter-autoroll","group":0},{"id":"skyostil","group":0},{"id":"slightfoot","group":0},{"id":"flutter","group":1},{"id":"plugins","group":1},{"id":"stephenhines","group":0},{"id":"stuartmorgan","group":0},{"id":"buildroot","group":1},{"id":"flutter","group":1},{"id":"flutter-desktop-embedding","group":1},{"id":"stupidfive","group":0},{"id":"szakarias","group":0},{"id":"flutter","group":1},{"id":"plugins","group":1},{"id":"tamird","group":0},{"id":"teisenbe","group":0},{"id":"terrylucas","group":0},{"id":"timsneath","group":0},{"id":"flutter","group":1},{"id":"plugins","group":1},{"id":"tonygentilcore","group":0},{"id":"flutter","group":1},{"id":"turnidge","group":0},{"id":"tvolkert","group":0},{"id":"buildroot","group":1},{"id":"flutter","group":1},{"id":"plugins","group":1},{"id":"ueman","group":0},{"id":"vardhan-cr","group":0},{"id":"viettrungluu-cr","group":0},{"id":"flutter","group":1},{"id":"vlidholt","group":0},{"id":"flutter","group":1},{"id":"vosst","group":0},{"id":"willlarche","group":0},{"id":"flutter","group":1},{"id":"wsxyeah","group":0},{"id":"xqwzts","group":0},{"id":"awesome-flutter","group":1},{"id":"flutter","group":1},{"id":"plugins","group":1},{"id":"xster","group":0},{"id":"flutter","group":1},{"id":"plugins","group":1},{"id":"yjbanov","group":0},{"id":"buildroot","group":1},{"id":"flutter","group":1},{"id":"plugins","group":1},{"id":"yunyu","group":0},{"id":"plugins","group":1},{"id":"yury-s","group":0},{"id":"yyoon","group":0},{"id":"flutter","group":1},{"id":"yzshen","group":0},{"id":"zanderso","group":0},{"id":"buildroot","group":1},{"id":"flutter","group":1},{"id":"plugins","group":1},{"id":"zhongwuzw","group":0},{"id":"zmbush","group":0}],"links":[{"source":1,"target":2,"value":0},{"source":3,"target":4,"value":0},{"source":7,"target":8,"value":0},{"source":9,"target":10,"value":0},{"source":9,"target":11,"value":0},{"source":13,"target":14,"value":0},{"source":13,"target":15,"value":0},{"source":17,"target":18,"value":0},{"source":17,"target":19,"value":0},{"source":22,"target":23,"value":0},{"source":24,"target":25,"value":0},{"source":27,"target":28,"value":0},{"source":32,"target":33,"value":0},{"source":32,"target":34,"value":0},{"source":32,"target":35,"value":0},{"source":36,"target":37,"value":0},{"source":36,"target":38,"value":0},{"source":36,"target":39,"value":0},{"source":40,"target":41,"value":0},{"source":42,"target":43,"value":0},{"source":42,"target":44,"value":0},{"source":45,"target":46,"value":0},{"source":49,"target":50,"value":0},{"source":51,"target":52,"value":0},{"source":55,"target":56,"value":0},{"source":57,"target":58,"value":0},{"source":57,"target":59,"value":0},{"source":60,"target":61,"value":0},{"source":62,"target":63,"value":0},{"source":64,"target":65,"value":0},{"source":64,"target":66,"value":0},{"source":67,"target":68,"value":0},{"source":67,"target":69,"value":0},{"source":67,"target":70,"value":0},{"source":73,"target":74,"value":0},{"source":75,"target":76,"value":0},{"source":77,"target":78,"value":0},{"source":82,"target":83,"value":0},{"source":82,"target":84,"value":0},{"source":82,"target":85,"value":0},{"source":86,"target":87,"value":0},{"source":88,"target":89,"value":0},{"source":94,"target":95,"value":0},{"source":94,"target":96,"value":0},{"source":100,"target":101,"value":0},{"source":100,"target":102,"value":0},{"source":100,"target":103,"value":0},{"source":104,"target":105,"value":0},{"source":104,"target":106,"value":0},{"source":107,"target":108,"value":0},{"source":109,"target":110,"value":0},{"source":111,"target":112,"value":0},{"source":111,"target":113,"value":0},{"source":111,"target":114,"value":0},{"source":111,"target":115,"value":0},{"source":111,"target":116,"value":0},{"source":111,"target":117,"value":0},{"source":111,"target":118,"value":0},{"source":111,"target":119,"value":0},{"source":111,"target":120,"value":0},{"source":111,"target":121,"value":0},{"source":111,"target":122,"value":0},{"source":111,"target":123,"value":0},{"source":111,"target":124,"value":0},{"source":111,"target":125,"value":0},{"source":111,"target":126,"value":0},{"source":111,"target":127,"value":0},{"source":111,"target":128,"value":0},{"source":111,"target":129,"value":0},{"source":111,"target":130,"value":0},{"source":111,"target":131,"value":0},{"source":111,"target":132,"value":0},{"source":133,"target":134,"value":0},{"source":136,"target":137,"value":0},{"source":136,"target":138,"value":0},{"source":140,"target":141,"value":0},{"source":142,"target":143,"value":0},{"source":144,"target":145,"value":0},{"source":144,"target":146,"value":0},{"source":150,"target":151,"value":0},{"source":150,"target":152,"value":0},{"source":150,"target":153,"value":0},{"source":150,"target":154,"value":0},{"source":155,"target":156,"value":0},{"source":158,"target":159,"value":0},{"source":161,"target":162,"value":0},{"source":161,"target":163,"value":0},{"source":161,"target":164,"value":0},{"source":161,"target":165,"value":0},{"source":167,"target":168,"value":0},{"source":170,"target":171,"value":0},{"source":172,"target":173,"value":0},{"source":179,"target":180,"value":0},{"source":181,"target":182,"value":0},{"source":183,"target":184,"value":0},{"source":187,"target":188,"value":0},{"source":189,"target":190,"value":0},{"source":189,"target":191,"value":0},{"source":193,"target":194,"value":0},{"source":193,"target":195,"value":0},{"source":197,"target":198,"value":0},{"source":199,"target":200,"value":0},{"source":199,"target":201,"value":0},{"source":202,"target":203,"value":0},{"source":202,"target":204,"value":0},{"source":202,"target":205,"value":0},{"source":206,"target":207,"value":0},{"source":206,"target":208,"value":0},{"source":206,"target":209,"value":0},{"source":211,"target":212,"value":0},{"source":214,"target":215,"value":0},{"source":216,"target":217,"value":0},{"source":219,"target":220,"value":0},{"source":219,"target":221,"value":0},{"source":222,"target":223,"value":0},{"source":222,"target":224,"value":0},{"source":225,"target":226,"value":0},{"source":225,"target":227,"value":0},{"source":229,"target":230,"value":0},{"source":231,"target":232,"value":0},{"source":231,"target":233,"value":0},{"source":235,"target":236,"value":0},{"source":237,"target":238,"value":0},{"source":237,"target":239,"value":0},{"source":240,"target":241,"value":0},{"source":240,"target":242,"value":0},{"source":240,"target":243,"value":0},{"source":245,"target":246,"value":0},{"source":248,"target":249,"value":0},{"source":250,"target":251,"value":0},{"source":252,"target":253,"value":0},{"source":254,"target":255,"value":0},{"source":256,"target":257,"value":0},{"source":258,"target":259,"value":0},{"source":260,"target":261,"value":0},{"source":260,"target":262,"value":0},{"source":260,"target":263,"value":0},{"source":265,"target":266,"value":0},{"source":268,"target":269,"value":0},{"source":270,"target":271,"value":0},{"source":273,"target":274,"value":0},{"source":273,"target":275,"value":0},{"source":273,"target":276,"value":0},{"source":277,"target":278,"value":0},{"source":280,"target":281,"value":0},{"source":280,"target":282,"value":0},{"source":284,"target":285,"value":0},{"source":286,"target":287,"value":0},{"source":286,"target":288,"value":0},{"source":295,"target":296,"value":0},{"source":297,"target":298,"value":0},{"source":299,"target":300,"value":0},{"source":299,"target":301,"value":0},{"source":302,"target":303,"value":0},{"source":308,"target":309,"value":0},{"source":308,"target":310,"value":0},{"source":308,"target":311,"value":0},{"source":312,"target":313,"value":0},{"source":312,"target":314,"value":0},{"source":315,"target":316,"value":0},{"source":315,"target":317,"value":0},{"source":315,"target":318,"value":0},{"source":319,"target":320,"value":0},{"source":321,"target":322,"value":0},{"source":323,"target":324,"value":0},{"source":325,"target":326,"value":0},{"source":327,"target":328,"value":0},{"source":327,"target":329,"value":0},{"source":327,"target":330,"value":0},{"source":331,"target":332,"value":0},{"source":334,"target":335,"value":0},{"source":336,"target":337,"value":0},{"source":336,"target":338,"value":0},{"source":336,"target":339,"value":0},{"source":340,"target":341,"value":0},{"source":340,"target":342,"value":0},{"source":343,"target":344,"value":0},{"source":345,"target":346,"value":0},{"source":347,"target":348,"value":0},{"source":349,"target":350,"value":0},{"source":349,"target":351,"value":0},{"source":349,"target":352,"value":0},{"source":353,"target":354,"value":0},{"source":353,"target":355,"value":0},{"source":357,"target":358,"value":0},{"source":357,"target":359,"value":0},{"source":363,"target":364,"value":0},{"source":370,"target":371,"value":0},{"source":373,"target":374,"value":0},{"source":373,"target":375,"value":0},{"source":376,"target":377,"value":0},{"source":381,"target":382,"value":0},{"source":383,"target":384,"value":0},{"source":383,"target":385,"value":0},{"source":386,"target":387,"value":0},{"source":386,"target":388,"value":0},{"source":389,"target":390,"value":0},{"source":392,"target":393,"value":0},{"source":399,"target":400,"value":0},{"source":399,"target":401,"value":0},{"source":405,"target":406,"value":0},{"source":408,"target":409,"value":0},{"source":408,"target":410,"value":0},{"source":408,"target":411,"value":0},{"source":408,"target":412,"value":0},{"source":408,"target":413,"value":0},{"source":414,"target":415,"value":0},{"source":414,"target":416,"value":0},{"source":417,"target":418,"value":0},{"source":420,"target":421,"value":0},{"source":420,"target":422,"value":0},{"source":423,"target":424,"value":0},{"source":426,"target":427,"value":0},{"source":430,"target":431,"value":0},{"source":430,"target":432,"value":0},{"source":434,"target":435,"value":0},{"source":434,"target":436,"value":0},{"source":434,"target":437,"value":0},{"source":439,"target":440,"value":0},{"source":439,"target":441,"value":0},{"source":445,"target":446,"value":0},{"source":445,"target":447,"value":0},{"source":448,"target":449,"value":0},{"source":451,"target":452,"value":0},{"source":451,"target":453,"value":0},{"source":451,"target":454,"value":0},{"source":457,"target":458,"value":0},{"source":459,"target":460,"value":0},{"source":462,"target":463,"value":0},{"source":465,"target":466,"value":0},{"source":465,"target":467,"value":0},{"source":465,"target":468,"value":0},{"source":469,"target":470,"value":0},{"source":469,"target":471,"value":0},{"source":472,"target":473,"value":0},{"source":472,"target":474,"value":0},{"source":472,"target":475,"value":0},{"source":476,"target":477,"value":0},{"source":479,"target":480,"value":0},{"source":482,"target":483,"value":0},{"source":482,"target":484,"value":0},{"source":482,"target":485,"value":0},{"source":0,"target":1,"value":0},{"source":0,"target":3,"value":0},{"source":0,"target":5,"value":0},{"source":0,"target":6,"value":0},{"source":0,"target":7,"value":0},{"source":0,"target":9,"value":0},{"source":0,"target":12,"value":0},{"source":0,"target":13,"value":0},{"source":0,"target":16,"value":0},{"source":0,"target":17,"value":0},{"source":0,"target":20,"value":0},{"source":0,"target":21,"value":0},{"source":0,"target":22,"value":0},{"source":0,"target":24,"value":0},{"source":0,"target":26,"value":0},{"source":0,"target":27,"value":0},{"source":0,"target":29,"value":0},{"source":0,"target":30,"value":0},{"source":0,"target":31,"value":0},{"source":0,"target":32,"value":0},{"source":0,"target":36,"value":0},{"source":0,"target":40,"value":0},{"source":0,"target":42,"value":0},{"source":0,"target":45,"value":0},{"source":0,"target":47,"value":0},{"source":0,"target":48,"value":0},{"source":0,"target":49,"value":0},{"source":0,"target":51,"value":0},{"source":0,"target":53,"value":0},{"source":0,"target":54,"value":0},{"source":0,"target":55,"value":0},{"source":0,"target":57,"value":0},{"source":0,"target":60,"value":0},{"source":0,"target":62,"value":0},{"source":0,"target":64,"value":0},{"source":0,"target":67,"value":0},{"source":0,"target":71,"value":0},{"source":0,"target":72,"value":0},{"source":0,"target":73,"value":0},{"source":0,"target":75,"value":0},{"source":0,"target":77,"value":0},{"source":0,"target":79,"value":0},{"source":0,"target":80,"value":0},{"source":0,"target":81,"value":0},{"source":0,"target":82,"value":0},{"source":0,"target":86,"value":0},{"source":0,"target":88,"value":0},{"source":0,"target":90,"value":0},{"source":0,"target":91,"value":0},{"source":0,"target":92,"value":0},{"source":0,"target":93,"value":0},{"source":0,"target":94,"value":0},{"source":0,"target":97,"value":0},{"source":0,"target":98,"value":0},{"source":0,"target":99,"value":0},{"source":0,"target":100,"value":0},{"source":0,"target":104,"value":0},{"source":0,"target":107,"value":0},{"source":0,"target":109,"value":0},{"source":0,"target":111,"value":0},{"source":0,"target":133,"value":0},{"source":0,"target":135,"value":0},{"source":0,"target":136,"value":0},{"source":0,"target":139,"value":0},{"source":0,"target":140,"value":0},{"source":0,"target":142,"value":0},{"source":0,"target":144,"value":0},{"source":0,"target":147,"value":0},{"source":0,"target":148,"value":0},{"source":0,"target":149,"value":0},{"source":0,"target":150,"value":0},{"source":0,"target":155,"value":0},{"source":0,"target":157,"value":0},{"source":0,"target":158,"value":0},{"source":0,"target":160,"value":0},{"source":0,"target":161,"value":0},{"source":0,"target":166,"value":0},{"source":0,"target":167,"value":0},{"source":0,"target":169,"value":0},{"source":0,"target":170,"value":0},{"source":0,"target":172,"value":0},{"source":0,"target":174,"value":0},{"source":0,"target":175,"value":0},{"source":0,"target":176,"value":0},{"source":0,"target":177,"value":0},{"source":0,"target":178,"value":0},{"source":0,"target":179,"value":0},{"source":0,"target":181,"value":0},{"source":0,"target":183,"value":0},{"source":0,"target":185,"value":0},{"source":0,"target":186,"value":0},{"source":0,"target":187,"value":0},{"source":0,"target":189,"value":0},{"source":0,"target":192,"value":0},{"source":0,"target":193,"value":0},{"source":0,"target":196,"value":0},{"source":0,"target":197,"value":0},{"source":0,"target":199,"value":0},{"source":0,"target":202,"value":0},{"source":0,"target":206,"value":0},{"source":0,"target":210,"value":0},{"source":0,"target":211,"value":0},{"source":0,"target":213,"value":0},{"source":0,"target":214,"value":0},{"source":0,"target":216,"value":0},{"source":0,"target":218,"value":0},{"source":0,"target":219,"value":0},{"source":0,"target":222,"value":0},{"source":0,"target":225,"value":0},{"source":0,"target":228,"value":0},{"source":0,"target":229,"value":0},{"source":0,"target":231,"value":0},{"source":0,"target":234,"value":0},{"source":0,"target":235,"value":0},{"source":0,"target":237,"value":0},{"source":0,"target":240,"value":0},{"source":0,"target":244,"value":0},{"source":0,"target":245,"value":0},{"source":0,"target":247,"value":0},{"source":0,"target":248,"value":0},{"source":0,"target":250,"value":0},{"source":0,"target":252,"value":0},{"source":0,"target":254,"value":0},{"source":0,"target":256,"value":0},{"source":0,"target":258,"value":0},{"source":0,"target":260,"value":0},{"source":0,"target":264,"value":0},{"source":0,"target":265,"value":0},{"source":0,"target":267,"value":0},{"source":0,"target":268,"value":0},{"source":0,"target":270,"value":0},{"source":0,"target":272,"value":0},{"source":0,"target":273,"value":0},{"source":0,"target":277,"value":0},{"source":0,"target":279,"value":0},{"source":0,"target":280,"value":0},{"source":0,"target":283,"value":0},{"source":0,"target":284,"value":0},{"source":0,"target":286,"value":0},{"source":0,"target":289,"value":0},{"source":0,"target":290,"value":0},{"source":0,"target":291,"value":0},{"source":0,"target":292,"value":0},{"source":0,"target":293,"value":0},{"source":0,"target":294,"value":0},{"source":0,"target":295,"value":0},{"source":0,"target":297,"value":0},{"source":0,"target":299,"value":0},{"source":0,"target":302,"value":0},{"source":0,"target":304,"value":0},{"source":0,"target":305,"value":0},{"source":0,"target":306,"value":0},{"source":0,"target":307,"value":0},{"source":0,"target":308,"value":0},{"source":0,"target":312,"value":0},{"source":0,"target":315,"value":0},{"source":0,"target":319,"value":0},{"source":0,"target":321,"value":0},{"source":0,"target":323,"value":0},{"source":0,"target":325,"value":0},{"source":0,"target":327,"value":0},{"source":0,"target":331,"value":0},{"source":0,"target":333,"value":0},{"source":0,"target":334,"value":0},{"source":0,"target":336,"value":0},{"source":0,"target":340,"value":0},{"source":0,"target":343,"value":0},{"source":0,"target":345,"value":0},{"source":0,"target":347,"value":0},{"source":0,"target":349,"value":0},{"source":0,"target":353,"value":0},{"source":0,"target":356,"value":0},{"source":0,"target":357,"value":0},{"source":0,"target":360,"value":0},{"source":0,"target":361,"value":0},{"source":0,"target":362,"value":0},{"source":0,"target":363,"value":0},{"source":0,"target":365,"value":0},{"source":0,"target":366,"value":0},{"source":0,"target":367,"value":0},{"source":0,"target":368,"value":0},{"source":0,"target":369,"value":0},{"source":0,"target":370,"value":0},{"source":0,"target":372,"value":0},{"source":0,"target":373,"value":0},{"source":0,"target":376,"value":0},{"source":0,"target":378,"value":0},{"source":0,"target":379,"value":0},{"source":0,"target":380,"value":0},{"source":0,"target":381,"value":0},{"source":0,"target":383,"value":0},{"source":0,"target":386,"value":0},{"source":0,"target":389,"value":0},{"source":0,"target":391,"value":0},{"source":0,"target":392,"value":0},{"source":0,"target":394,"value":0},{"source":0,"target":395,"value":0},{"source":0,"target":396,"value":0},{"source":0,"target":397,"value":0},{"source":0,"target":398,"value":0},{"source":0,"target":399,"value":0},{"source":0,"target":402,"value":0},{"source":0,"target":403,"value":0},{"source":0,"target":404,"value":0},{"source":0,"target":405,"value":0},{"source":0,"target":407,"value":0},{"source":0,"target":408,"value":0},{"source":0,"target":414,"value":0},{"source":0,"target":417,"value":0},{"source":0,"target":419,"value":0},{"source":0,"target":420,"value":0},{"source":0,"target":423,"value":0},{"source":0,"target":425,"value":0},{"source":0,"target":426,"value":0},{"source":0,"target":428,"value":0},{"source":0,"target":429,"value":0},{"source":0,"target":430,"value":0},{"source":0,"target":433,"value":0},{"source":0,"target":434,"value":0},{"source":0,"target":438,"value":0},{"source":0,"target":439,"value":0},{"source":0,"target":442,"value":0},{"source":0,"target":443,"value":0},{"source":0,"target":444,"value":0},{"source":0,"target":445,"value":0},{"source":0,"target":448,"value":0},{"source":0,"target":450,"value":0},{"source":0,"target":451,"value":0},{"source":0,"target":455,"value":0},{"source":0,"target":456,"value":0},{"source":0,"target":457,"value":0},{"source":0,"target":459,"value":0},{"source":0,"target":461,"value":0},{"source":0,"target":462,"value":0},{"source":0,"target":464,"value":0},{"source":0,"target":465,"value":0},{"source":0,"target":469,"value":0},{"source":0,"target":472,"value":0},{"source":0,"target":476,"value":0},{"source":0,"target":478,"value":0},{"source":0,"target":479,"value":0},{"source":0,"target":481,"value":0},{"source":0,"target":482,"value":0},{"source":0,"target":486,"value":0},{"source":0,"target":487,"value":0}]}